Workbook
Name aporte: INVESTIMENTO!$D$10
Name rendimento_carteira: INVESTIMENTO!$D$6

Sheet INVESTIMENTO
B2: TÍTULO COM LOGO
B4: CONFIGURAÇÕES
B5: Salário | D5: 2000
B6: Rendimento Carteira | D6: 0.006
B7: Sugestão de Investimento (30%) | D7: =$D$5*30% -> 600
B9: INVESTIMENTO MENSAL
B10: Quanto investir por mês ? | D10: 200
B11: Por quantos anos ? | D11: 5
B12: Taxa de rendimento mensal ? | D12: 0.01079
B13: Quanto de patrimonio acumulado terei ? | D13: =FV($D$12,$D$11*12,$D$10*-1) -> 16755.383
B14: Quais são os dividendos mensais ? | D14: =D13*D12 -> 180.79058
B16: CENÁRIOS | D16: Dividendo
A17: 2 | B17: Quanto em 2 anos ? | C17: =FV($D$12,$A17*12,$D$10*-1) -> 5445.5255 | D17: =C17*$D$6 -> 32.673153
A18: 5 | B18: Quanto em 5 anos ? | C18: =FV($D$12,$A18*12,$D$10*-1) -> 16755.383 | D18: =C18*$D$6 -> 100.5323
A19: 10 | B19: Quanto em 10 anos ? | C19: =FV($D$12,$A19*12,$D$10*-1) -> 48656.843 | D19: =C19*$D$6 -> 291.94106
A20: 20 | B20: Quanto em 20 anos ? | C20: =FV($D$12,$A20*12,$D$10*-1) -> 225039.68 | D20: =C20*$D$6 -> 1350.2381
A21: 30 | B21: Quanto em 30 anos ? | C21: =FV($D$12,$A21*12,$D$10*-1) -> 864433.93 | D21: =C21*$D$6 -> 5186.6036
B23: PERFIL: | C23: AGRESSIVO
B24: Valor a ser investido por mês: | C24: =aporte -> 200
B26: TIPO DE FII | C26: % Sugerido | D26: Valores
B27: PAPEL | C27: =VLOOKUP($C$23&"-"&$B27,TBL_APOIO!$D$2:$E$20,2,FALSE) -> 0.5 | D27: =$C27*$C$24 -> 100
B28: TIJOLO | C28: =VLOOKUP($C$23&"-"&$B28,TBL_APOIO!$D$2:$E$20,2,FALSE) -> 0.1 | D28: =$C28*$C$24 -> 20
B29: HIBRÍDOS | C29: =VLOOKUP($C$23&"-"&$B29,TBL_APOIO!$D$2:$E$20,2,FALSE) -> 0.05 | D29: =$C29*$C$24 -> 10
B30: FOFs | C30: =VLOOKUP($C$23&"-"&$B30,TBL_APOIO!$D$2:$E$20,2,FALSE) -> 0.05 | D30: =$C30*$C$24 -> 10
B31: DESENVOLVIMENTO | C31: =VLOOKUP($C$23&"-"&$B31,TBL_APOIO!$D$2:$E$20,2,FALSE) -> 0.2 | D31: =$C31*$C$24 -> 40
B32: HOTELARIAS | C32: =VLOOKUP($C$23&"-"&$B32,TBL_APOIO!$D$2:$E$20,2,FALSE) -> 0.1 | D32: =$C32*$C$24 -> 20
C33: =SUM(C27:C32) -> 1 | D33: =SUM(D27:D32) -> 200

Sheet TBL_APOIO
B2: PERFIL | C2: TIPO DE FII | D2: CHAVE | E2: %
B3: CONSERVADOR | C3: PAPEL | D3: =B3&"-"&C3 -> CONSERVADOR-PAPEL | E3: 0.3
B4: CONSERVADOR | C4: TIJOLO | D4: =B4&"-"&C4 -> CONSERVADOR-TIJOLO | E4: 0.5
B5: CONSERVADOR | C5: HIBRÍDOS | D5: =B5&"-"&C5 -> CONSERVADOR-HIBRÍDOS | E5: 0.1
B6: CONSERVADOR | C6: FOFs | D6: =B6&"-"&C6 -> CONSERVADOR-FOFs | E6: 0.1
B7: CONSERVADOR | C7: DESENVOLVIMENTO | D7: =B7&"-"&C7 -> CONSERVADOR-DESENVOLVIMENTO | E7: 0
B8: CONSERVADOR | C8: HOTELARIAS | D8: =B8&"-"&C8 -> CONSERVADOR-HOTELARIAS | E8: 0
B9: MODERADO | C9: PAPEL | D9: =B9&"-"&C9 -> MODERADO-PAPEL | E9: 0.32
B10: MODERADO | C10: TIJOLO | D10: =B10&"-"&C10 -> MODERADO-TIJOLO | E10: 0.35
B11: MODERADO | C11: HIBRÍDOS | D11: =B11&"-"&C11 -> MODERADO-HIBRÍDOS | E11: 0.08
B12: MODERADO | C12: FOFs | D12: =B12&"-"&C12 -> MODERADO-FOFs | E12: 0.05
B13: MODERADO | C13: DESENVOLVIMENTO | D13: =B13&"-"&C13 -> MODERADO-DESENVOLVIMENTO | E13: 0.1
B14: MODERADO | C14: HOTELARIAS | D14: =B14&"-"&C14 -> MODERADO-HOTELARIAS | E14: 0.1
... B20: AGRESSIVO | C20: HOTELARIAS | D20: =B20&"-"&C20 -> AGRESSIVO-HOTELARIAS | E20: 0.1
